pacing/__init__.py
pacing/platform.py
pacing/core/__init__.py
pacing/core/agent_interfaces.py
pacing/core/audio_interfaces.py
pacing/core/model_interfaces.py
pacing/core/session_interfaces.py
pacing/core/transcription_interfaces.py
pacing/impl/__init__.py
pacing/impl/agents/__init__.py
pacing/impl/agents/uncertainty_auditor.py
pacing/impl/defaults/__init__.py
pacing/impl/defaults/mock_audio.py
pacing/impl/defaults/mock_risk_model.py
pacing/impl/defaults/mock_transcriber.py
pacing/models/__init__.py
pacing/models/data_models.py
pacing/privacy/__init__.py
pacing/simulation/__init__.py
pacing/simulation/simulation_engine.py
pacing-0.0.7.dist-info/METADATA
pacing-0.0.7.dist-info/WHEEL
pacing-0.0.7.dist-info/licenses/LICENSE
pacing-0.0.7.dist-info/RECORD
