Metadata-Version: 2.4
Name: pacing
Version: 0.0.7
Summary: Platform for Agentic Clinical Intelligence with Networked Graphs
Project-URL: Homepage, https://github.com/thorwhalen/pacing
Project-URL: Repository, https://github.com/thorwhalen/pacing
Project-URL: Documentation, https://thorwhalen.github.io/pacing
Author: Thor Whalen
License: mit
License-File: LICENSE
Requires-Python: >=3.10
Requires-Dist: numpy>=1.20
Requires-Dist: pydantic>=2.0
Provides-Extra: dev
Requires-Dist: pytest-cov>=4.0; extra == 'dev'
Requires-Dist: pytest>=7.0; extra == 'dev'
Requires-Dist: ruff>=0.1.0; extra == 'dev'
Provides-Extra: docs
Requires-Dist: sphinx-rtd-theme>=1.0; extra == 'docs'
Requires-Dist: sphinx>=6.0; extra == 'docs'
